apidoc.zcml
buildout.cfg
debug.ini
deploy.ini
setup.py
site.zcml
zdaemon.conf
zope.conf
log/README.txt
src/largeblue/__init__.py
src/largeblue/startup.py
src/largeblue.tag.egg-info/PKG-INFO
src/largeblue.tag.egg-info/SOURCES.txt
src/largeblue.tag.egg-info/dependency_links.txt
src/largeblue.tag.egg-info/entry_points.txt
src/largeblue.tag.egg-info/namespace_packages.txt
src/largeblue.tag.egg-info/not-zip-safe
src/largeblue.tag.egg-info/paster_plugins.txt
src/largeblue.tag.egg-info/requires.txt
src/largeblue.tag.egg-info/top_level.txt
src/largeblue/tag/README.txt
src/largeblue/tag/__init__.py
src/largeblue/tag/adapter.py
src/largeblue/tag/configure.zcml
src/largeblue/tag/dependencies.zcml
src/largeblue/tag/ftesting.zcml
src/largeblue/tag/interfaces.py
src/largeblue/tag/testing.py
src/largeblue/tag/browser/__init__.py
src/largeblue/tag/browser/configure.zcml
src/largeblue/tag/browser/view.py
var/README.txt