Metadata-Version: 1.0
Name: largeblue.tag
Version: 0.1.1
Summary: Simple tagging adapter
Home-page: http://pesto.largeblue.net/trac/browser/largeblue/devel/largeblue.tag
Author: James Arthur
Author-email: firstname.lastname@largeblue.com
License: Public Domain
Keywords: zope largeblue tag tags tagging adapter simple
Platform: UNKNOWN
Classifier: Programming Language :: Python
Classifier: Environment :: Web Environment
Classifier: Topic :: Internet :: WWW/HTTP :: WSGI :: Application
Classifier: Framework :: Zope3
Classifier: Intended Audience :: Developers
Classifier: License :: Public Domain
Classifier: Natural Language :: English
